knorket_whisper/__init__.py
knorket_whisper/utils.py
knorket_whisper/cli/__init__.py
knorket_whisper/cli/transcribe.py
knorket_whisper-2.0.dist-info/METADATA
knorket_whisper-2.0.dist-info/WHEEL
knorket_whisper-2.0.dist-info/entry_points.txt
knorket_whisper-2.0.dist-info/top_level.txt
knorket_whisper-2.0.dist-info/RECORD
